{
  "service": {
    "service": "goback-graphql",
    "serviceObject": {
      "name": "goback-graphql"
    },
    "provider": {
      "name": "aws",
      "runtime": "provided.al2",
      "stage": "dev",
      "region": "us-east-1",
      "versionFunctions": true,
      "compiledCloudFormationTemplate": {
        "AWSTemplateFormatVersion": "2010-09-09",
        "Description": "The AWS CloudFormation template for this Serverless application",
        "Resources": {
          "ApiLogGroup": {
            "Type": "AWS::Logs::LogGroup",
            "Properties": {
              "LogGroupName": "/aws/lambda/goback-graphql-dev-api"
            }
          },
          "IamRoleLambdaExecution": {
            "Type": "AWS::IAM::Role",
            "Properties": {
              "AssumeRolePolicyDocument": {
                "Version": "2012-10-17",
                "Statement": [
                  {
                    "Effect": "Allow",
                    "Principal": {
                      "Service": [
                        "lambda.amazonaws.com"
                      ]
                    },
                    "Action": [
                      "sts:AssumeRole"
                    ]
                  }
                ]
              },
              "Policies": [
                {
                  "PolicyName": {
                    "Fn::Join": [
                      "-",
                      [
                        "goback-graphql",
                        "dev",
                        "lambda"
                      ]
                    ]
                  },
                  "PolicyDocument": {
                    "Version": "2012-10-17",
                    "Statement": [
                      {
                        "Effect": "Allow",
                        "Action": [
                          "logs:CreateLogStream",
                          "logs:CreateLogGroup",
                          "logs:TagResource"
                        ],
                        "Resource": [
                          {
                            "Fn::Sub": "arn:${AWS::Partition}:logs:${AWS::Region}:${AWS::AccountId}:log-group:/aws/lambda/goback-graphql-dev*:*"
                          }
                        ]
                      },
                      {
                        "Effect": "Allow",
                        "Action": [
                          "logs:PutLogEvents"
                        ],
                        "Resource": [
                          {
                            "Fn::Sub": "arn:${AWS::Partition}:logs:${AWS::Region}:${AWS::AccountId}:log-group:/aws/lambda/goback-graphql-dev*:*:*"
                          }
                        ]
                      }
                    ]
                  }
                }
              ],
              "Path": "/",
              "RoleName": {
                "Fn::Join": [
                  "-",
                  [
                    "goback-graphql",
                    "dev",
                    {
                      "Ref": "AWS::Region"
                    },
                    "lambdaRole"
                  ]
                ]
              }
            }
          },
          "ApiLambdaFunction": {
            "Type": "AWS::Lambda::Function",
            "Properties": {
              "Code": {
                "S3Bucket": "serverless-framework-deployments-us-east-1-bdbb5353-2602",
                "S3Key": "serverless/goback-graphql/dev/1734027160961-2024-12-12T18:12:40.961Z/main.zip"
              },
              "Handler": "api/graphql/bootstrap",
              "Runtime": "provided.al2",
              "FunctionName": "goback-graphql-dev-api",
              "MemorySize": 1024,
              "Timeout": 6,
              "Role": {
                "Fn::GetAtt": [
                  "IamRoleLambdaExecution",
                  "Arn"
                ]
              }
            },
            "DependsOn": [
              "ApiLogGroup"
            ]
          },
          "ApiLambdaVersionMVbW8lnSGtto30YjMPiIfuSkkxBEH26RsxEkObxPjc": {
            "Type": "AWS::Lambda::Version",
            "DeletionPolicy": "Retain",
            "Properties": {
              "FunctionName": {
                "Ref": "ApiLambdaFunction"
              },
              "CodeSha256": "JyAInAZoYSsLnd54FUHzL7VLZTtiNY7EhBhL+TvVrwA="
            }
          },
          "HttpApi": {
            "Type": "AWS::ApiGatewayV2::Api",
            "Properties": {
              "Name": "dev-goback-graphql",
              "ProtocolType": "HTTP"
            }
          },
          "HttpApiStage": {
            "Type": "AWS::ApiGatewayV2::Stage",
            "Properties": {
              "ApiId": {
                "Ref": "HttpApi"
              },
              "StageName": "$default",
              "AutoDeploy": true,
              "DefaultRouteSettings": {
                "DetailedMetricsEnabled": false
              }
            }
          },
          "ApiLambdaPermissionHttpApi": {
            "Type": "AWS::Lambda::Permission",
            "Properties": {
              "FunctionName": {
                "Fn::GetAtt": [
                  "ApiLambdaFunction",
                  "Arn"
                ]
              },
              "Action": "lambda:InvokeFunction",
              "Principal": "apigateway.amazonaws.com",
              "SourceArn": {
                "Fn::Join": [
                  "",
                  [
                    "arn:",
                    {
                      "Ref": "AWS::Partition"
                    },
                    ":execute-api:",
                    {
                      "Ref": "AWS::Region"
                    },
                    ":",
                    {
                      "Ref": "AWS::AccountId"
                    },
                    ":",
                    {
                      "Ref": "HttpApi"
                    },
                    "/*"
                  ]
                ]
              }
            }
          },
          "HttpApiIntegrationApi": {
            "Type": "AWS::ApiGatewayV2::Integration",
            "Properties": {
              "ApiId": {
                "Ref": "HttpApi"
              },
              "IntegrationType": "AWS_PROXY",
              "IntegrationUri": {
                "$ref": "$[\"service\"][\"provider\"][\"compiledCloudFormationTemplate\"][\"Resources\"][\"ApiLambdaPermissionHttpApi\"][\"Properties\"][\"FunctionName\"]"
              },
              "PayloadFormatVersion": "2.0",
              "TimeoutInMillis": 30000
            }
          },
          "HttpApiRouteAnyGraphql": {
            "Type": "AWS::ApiGatewayV2::Route",
            "Properties": {
              "ApiId": {
                "Ref": "HttpApi"
              },
              "RouteKey": "ANY /graphql",
              "Target": {
                "Fn::Join": [
                  "/",
                  [
                    "integrations",
                    {
                      "Ref": "HttpApiIntegrationApi"
                    }
                  ]
                ]
              }
            },
            "DependsOn": "HttpApiIntegrationApi"
          },
          "HttpApiRouteAnyGraphqlProxyVar": {
            "Type": "AWS::ApiGatewayV2::Route",
            "Properties": {
              "ApiId": {
                "Ref": "HttpApi"
              },
              "RouteKey": "ANY /graphql/{proxy+}",
              "Target": {
                "Fn::Join": [
                  "/",
                  [
                    "integrations",
                    {
                      "Ref": "HttpApiIntegrationApi"
                    }
                  ]
                ]
              }
            },
            "DependsOn": "HttpApiIntegrationApi"
          }
        },
        "Outputs": {
          "ServerlessDeploymentBucketName": {
            "Value": "serverless-framework-deployments-us-east-1-bdbb5353-2602",
            "Export": {
              "Name": "sls-goback-graphql-dev-ServerlessDeploymentBucketName"
            }
          },
          "ApiLambdaFunctionQualifiedArn": {
            "Description": "Current Lambda function version",
            "Value": {
              "Ref": "ApiLambdaVersionMVbW8lnSGtto30YjMPiIfuSkkxBEH26RsxEkObxPjc"
            },
            "Export": {
              "Name": "sls-goback-graphql-dev-ApiLambdaFunctionQualifiedArn"
            }
          },
          "HttpApiId": {
            "Description": "Id of the HTTP API",
            "Value": {
              "Ref": "HttpApi"
            },
            "Export": {
              "Name": "sls-goback-graphql-dev-HttpApiId"
            }
          },
          "HttpApiUrl": {
            "Description": "URL of the HTTP API",
            "Value": {
              "Fn::Join": [
                "",
                [
                  "https://",
                  {
                    "Ref": "HttpApi"
                  },
                  ".execute-api.",
                  {
                    "Ref": "AWS::Region"
                  },
                  ".",
                  {
                    "Ref": "AWS::URLSuffix"
                  }
                ]
              ]
            },
            "Export": {
              "Name": "sls-goback-graphql-dev-HttpApiUrl"
            }
          }
        }
      },
      "vpc": {}
    },
    "pluginsData": {},
    "functions": {
      "api": {
        "handler": "api/graphql/bootstrap",
        "package": {
          "artifact": "api/graphql/main.zip"
        },
        "events": [
          {
            "httpApi": {
              "path": "/graphql",
              "method": "any"
            },
            "resolvedMethod": "ANY",
            "resolvedPath": "/graphql"
          },
          {
            "httpApi": {
              "path": "/graphql/{proxy+}",
              "method": "any"
            },
            "resolvedMethod": "ANY",
            "resolvedPath": "/graphql/{proxy+}"
          }
        ],
        "name": "goback-graphql-dev-api",
        "memory": 1024,
        "timeout": 6,
        "runtime": "provided.al2",
        "vpc": {},
        "versionLogicalId": "ApiLambdaVersionMVbW8lnSGtto30YjMPiIfuSkkxBEH26RsxEkObxPjc"
      }
    },
    "configValidationMode": "warn",
    "serviceFilename": "serverless.graphql.yml",
    "initialServerlessConfig": {
      "org": "seebasoft",
      "app": "prompter",
      "service": "goback-graphql",
      "provider": {
        "$ref": "$[\"service\"][\"provider\"]"
      },
      "package": {
        "individually": true,
        "artifactsS3KeyDirname": "serverless/goback-graphql/dev/code-artifacts",
        "deploymentBucket": "serverless-framework-deployments-us-east-1-bdbb5353-2602",
        "artifactDirectoryName": "serverless/goback-graphql/dev/1734027160961-2024-12-12T18:12:40.961Z"
      },
      "functions": {
        "$ref": "$[\"service\"][\"functions\"]"
      }
    },
    "app": "prompter",
    "appId": null,
    "org": "seebasoft",
    "orgId": null,
    "layers": {}
  },
  "package": {
    "individually": true,
    "artifactDirectoryName": "serverless/goback-graphql/dev/1734027160961-2024-12-12T18:12:40.961Z",
    "artifact": ""
  }
}